pyreadr/__init__.py
pyreadr/_pyreadr_parser.py
pyreadr/_pyreadr_writer.py
pyreadr/conditional_includes.h
pyreadr/custom_errors.py
pyreadr/librdata.c
pyreadr/librdata.cpython-310-darwin.so
pyreadr/librdata.pxd
pyreadr/librdata.pyx
pyreadr/pyreadr.py
pyreadr/libs/bzip2/bzlib.h
pyreadr/libs/iconv/iconv.h
pyreadr/libs/librdata/src/CKHashTable.c
pyreadr/libs/librdata/src/CKHashTable.h
pyreadr/libs/librdata/src/rdata.h
pyreadr/libs/librdata/src/rdata_bits.c
pyreadr/libs/librdata/src/rdata_bits.h
pyreadr/libs/librdata/src/rdata_error.c
pyreadr/libs/librdata/src/rdata_internal.h
pyreadr/libs/librdata/src/rdata_io_unistd.c
pyreadr/libs/librdata/src/rdata_io_unistd.h
pyreadr/libs/librdata/src/rdata_parser.c
pyreadr/libs/librdata/src/rdata_read.c
pyreadr/libs/librdata/src/rdata_write.c
pyreadr/libs/lzma/lzma.h
pyreadr/libs/lzma/lzma/base.h
pyreadr/libs/lzma/lzma/bcj.h
pyreadr/libs/lzma/lzma/block.h
pyreadr/libs/lzma/lzma/check.h
pyreadr/libs/lzma/lzma/container.h
pyreadr/libs/lzma/lzma/delta.h
pyreadr/libs/lzma/lzma/filter.h
pyreadr/libs/lzma/lzma/hardware.h
pyreadr/libs/lzma/lzma/index.h
pyreadr/libs/lzma/lzma/index_hash.h
pyreadr/libs/lzma/lzma/lzma12.h
pyreadr/libs/lzma/lzma/stream_flags.h
pyreadr/libs/lzma/lzma/version.h
pyreadr/libs/lzma/lzma/vli.h
pyreadr/libs/zlib/zconf.h
pyreadr/libs/zlib/zlib.h
pyreadr-0.5.3.dist-info/LICENSE
pyreadr-0.5.3.dist-info/LICENSE_jamovi_readstat
pyreadr-0.5.3.dist-info/LICENSE_librdata
pyreadr-0.5.3.dist-info/METADATA
pyreadr-0.5.3.dist-info/WHEEL
pyreadr-0.5.3.dist-info/top_level.txt
pyreadr-0.5.3.dist-info/RECORD
